Workbook

Sheet Instrucciones
A1: LunfaBench · Planilla del conjunto curado
A3: Son los 90 términos del conjunto curado: 40 falsos amigos, 20 sin homónimo, 15 polisémicos y 15 controles, mezclados. Cada uno trae dos fragmentos reales (A y B) de canciones de artistas de Buenos Aires.
A4: Qué hace cada anotador
A5: 1. Escribí tu nombre en «anotador». Cada fila la anotan dos personas, por separado: no mires la columna de la otra persona hasta terminar.
A6: 2. En «capa», elegí de la lista qué tipo de palabra es, pensando en Buenos Aires:
A7: falso_amigo: tiene una acepción de España o México que acá no se usa (curro: acá negocio turbio, en España trabajo).
A8: polisemico_interno: tiene varias acepciones y todas se usan acá (pileta: piscina y pileta de la cocina).
A9: lunfardo_sin_homonimo: no existe con otro sentido en España ni en México (bondi, chamuyo).
A10: espanol_general: es una palabra común del español, que significa lo mismo en todos lados (ventana).
A11: 3. En «fragmento», elegí A o B: el que usa la acepción de referencia. Si los dos la usan, el que mejor se entienda. Si ninguno, el más cercano, y contalo en «comentario».
A12: 4. Si elegiste falso_amigo, escribí la acepción competidora y dónde se usa, por ejemplo «trabajo (España)».
A13: Se puede consultar el DLE y el Diccionario de americanismos. No consultes Wiktionary ni Wikcionario: son la fuente del filtro automático y el acuerdo quedaría inflado.
... A18: Ejemplo de fila completa (el término no está en la planilla)
A20: término | B20: acepción de referencia | C20: anotador 1 | D20: capa 1 | E20: fragmento 1 | F20: acepción competidora 1
A21: torta | C21: Tomás | D21: falso_amigo | E21: A | F21: (la acepción de España o México)

Sheet Anotación
A1: id | B1: término | C1: acepción de referencia | D1: fuente | E1: fragmento A | F1: canción A | G1: fragmento B | H1: canción B | I1: anotador 1 | J1: capa 1 | K1: fragmento 1 | L1: acepción competidora 1 | M1: anotador 2 | N1: capa 2 | O1: fragmento 2 | P1: acepción competidora 2 | Q1: coincide capa | R1: coincide fragmento | S1: capa final | T1: fragmento final | U1: comentario
A2: CUR-001 | B2: gira | C2: Ir a muchos lugares en un mismo día Habitualmente se lo usa cuando salen a varias fiestas una misma noche | D2: diccionarioargentino.com | E2: quiero a todos los pibe' cantina / Y que levanten bien la mano los que se bancan la gira / No tomo Chandon, me sirve el Federico | F2: Tamo Chelo · El Noba (2021) | G2: Maniac in my mind en medio de la ciudad / Girl, gira el volante del todo / Boxea sin guantes que es lo que quieren todos | H2: KAMIKAZE · Sofía Gabanna (2023) | I2: Tomas Borda | J2: polisemico_interno | K2: A | M2: Valentín Garfi | N2: lunfardo_sin_homonimo | O2: A | Q2: =IF(OR(J2="",N2=""),"",IF(J2=N2,"sí","no")) | R2: =IF(OR(K2="",O2=""),"",IF(K2=O2,"sí","no"))
A3: CUR-002 | B3: idear | C3: Concebir algo nuevo con la imaginación. | D3: Wikcionario | E3: Sabiendo que no quiero que te quedes / El hacedor de ideas se estrella en su carrera / La dirección del tiempo es frágil y se tienta | F3: Pinamar · Francisco Bochatón | G3: Al anochecer seducido de tensión / Vuela sin control ideando la misión / Vértigo inmoral, juicio sin identidad | H3: Adicto · D-mente | I3: Tomas Borda | J3: espanol_general | K3: B | M3: Valentín Garfi | N3: espanol_general | O3: B | Q3: =IF(OR(J3="",N3=""),"",IF(J3=N3,"sí","no")) | R3: =IF(OR(K3="",O3=""),"",IF(K3=O3,"sí","no"))
A4: CUR-003 | B4: chamuyo | C4: Hablarle a una persona con un propósito, mintiéndole para que te crea. | D4: diccionarioargentino.com | E4: Tango de triste motivo / Cuando siento tu chamuyo / Se queda en mi alma el arrullo | F4: Apología del Tango · Tita Merello (1969) | I4: Tomas Borda | J4: lunfardo_sin_homonimo | K4: A | M4: Valentín Garfi | N4: lunfardo_sin_homonimo | O4: A | Q4: =IF(OR(J4="",N4=""),"",IF(J4=N4,"sí","no")) | R4: =IF(OR(K4="",O4=""),"",IF(K4=O4,"sí","no"))
A5: CUR-004 | B5: cerrar | C5: Colocar o modificar algo para evitar su apertura. | D5: Wikcionario | E5: Puedo relajar otra vez / Y bailar cuando cierro los ojos / Pensando en vos | F5: Puedo Sentirlo · David Lebón (1986) | G5: Solo la muerte esconde el ultimo latido debil de mi corazón / Cuando cerre mis manos / Me guarde estos recuerdos | H5: Reescribir Tragedias Sobre Libros Y Llamas · Dar Sangre (2008) | I5: Tomas Borda | J5: espanol_general | K5: B | M5: Valentín Garfi | N5: espanol_general | O5: B | Q5: =IF(OR(J5="",N5=""),"",IF(J5=N5,"sí","no")) | R5: =IF(OR(K5="",O5=""),"",IF(K5=O5,"sí","no"))
A6: CUR-005 | B6: botón | C6: Soplón, delator | D6: diccionarioargentino.com | E6: Que si en la calle me afila / Me pongo al lao del botón / ¡Lo que más bronca me da | F6: Chorra · Edmundo Rivero (1959) | G6: Y el fueye, es un bandoneón / El vigilante, un botón / La policía, la cana | H6: Milonga Lunfarda · Edmundo Rivero (1972) | I6: Tomas Borda | J6: falso_amigo | K6: B | L6: Pieza pequeña de metal, hueso, nácar u otra materia, forrada de tela o sin forrar, que se pone en los vestidos para que, entrando en el ojal, los abroche y asegure. También se pone por adorno. | M6: Valentín Garfi | N6: falso_amigo | O6: B | P6: Elevación redondeada y plana de la piel, grano/verruga (Esp.) | Q6: =IF(OR(J6="",N6=""),"",IF(J6=N6,"sí","no")) | R6: =IF(OR(K6="",O6=""),"",IF(K6=O6,"sí","no"))
A7: CUR-006 | B7: burra | C7: Forma villera de denominar la cola de una dama. | D7: diccionarioargentino.com | E7: Las pibita' me llaman, 'tamo' chelo / Me etiquetó en su burra, 'tamo' chelo / Ese gato hatea, 'tamo' chelo | F7: Tamo Chelo · El Noba (2021) | G7: ¿Y ahora qué vamo' a hacer? / La baby lo mueve, qué burra, no sabés / Tiene flow, no hay compe (No hay compe) | H7: Del Año · El Noba (2021) | I7: Tomas Borda | J7: polisemico_interno | K7: A | M7: Valentín Garfi | N7: polisemico_interno | O7: A | Q7: =IF(OR(J7="",N7=""),"",IF(J7=N7,"sí","no")) | R7: =IF(OR(K7="",O7=""),"",IF(K7=O7,"sí","no"))
A8: CUR-007 | B8: gritar | C8: Hablar con la voz muy fuerte, para intimidar, alertar o comunicarse cuando el ruido de fondo impide la conversación normal. | D8: Wikcionario | E8: quieren montar como una puta encima de mi disco / Me gustaba escucharte gritar, bajaba to' el volumen / Bebiendo buena champaña y OG Kush pa' que | F8: Oye Baby · Zaramay (2020) | G8: Los que al mirar no se hacen / Ciegos por gritar / Sin pretender sen premiados | H8: Rugen Sus Voces · D-mente | I8: Tomas Borda | J8: espanol_general | K8: B | M8: Valentín Garfi | N8: espanol_general | O8: B | Q8: =IF(OR(J8="",N8=""),"",IF(J8=N8,"sí","no")) | R8: =IF(OR(K8="",O8=""),"",IF(K8=O8,"sí","no"))
A9: CUR-008 | B9: morocho | C9: Persona de tez morena y/o de cabello negro o castaño oscuro. | D9: diccionarioargentino.com | E9: Duki dispara aunque Mauro dude (Dude) / Soy el niño 'el año, morocho achinado / Llevo el doble caño, flow polarizado | F9: Hello Cotto · Duki (2017) | G9: ¿Dónde estarán Traverso, el Cordobés y el Noy / El Pardo Augusto, Flores y el Morocho Aldao? / Así empezó mi vuelo de zorzal | H9: El Cantor de Buenos Aires · Roberto Goyeneche | I9: Tomas Borda | J9: polisemico_interno | K9: A | M9: Valentín Garfi | N9: polisemico_interno | O9: A | Q9: =IF(OR(J9="",N9=""),"",IF(J9=N9,"sí","no")) | R9: =IF(OR(K9="",O9=""),"",IF(K9=O9,"sí","no"))
A10: CUR-009 | B10: timba | C10: Casa de juegos de azar o directamente jugar juegos de cartas | D10: diccionarioargentino.com | E10: Su boca de fuego, otra vez, quiero besar / Basta de carreras, se acabó la timba / Un final reñido yo no vuelvo a ver | F10: Por Una Cabeza · Carlos Gardel (1935) | G10: De sabihondos y suicidas / Yo aprendí filosofía, dados, timba... / Y la poesía cruel | H10: Cafetín de Buenos Aires · Edmundo Rivero (1959) | I10: Tomas Borda | J10: falso_amigo | K10: A | L10: casa de juego. | M10: Valentín Garfi | N10: falso_amigo | O10: A | P10: Panza o barriga (Méx., CR, El Salv., Guat., Hond., Nic.) | Q10: =IF(OR(J10="",N10=""),"",IF(J10=N10,"sí","no")) | R10: =IF(OR(K10="",O10=""),"",IF(K10=O10,"sí","no"))
A11: CUR-010 | B11: manija | C11: Tener manija es tener ansias o entusiasmo por algo. | D11: diccionarioargentino.com | E11: Con par de champetas yo siempre corono / 'Tamo re manija y nunca paramo' / Si pinta el after ahí nos mandamo' | F11: ALLA · EL NOBA (2022) | G11: En una cancha o en un bar / Dando la vuelta manija me doy / Subiendo al latido de esta vibración | H11: Toco y me voy · Bersuit Vergarabat (2000) | I11: Tomas Borda | J11: polisemico_interno | K11: A | M11: Valentín Garfi | N11: polisemico_interno | O11: A | Q11: =IF(OR(J11="",N11=""),"",IF(J11=N11,"sí","no")) | R11: =IF(OR(K11="",O11=""),"",IF(K11=O11,"sí","no"))
A12: CUR-011 | B12: viejo | C12: Sinonimo de padre/papá en el lunfardo argentino. | D12: diccionarioargentino.com | E12: por sonsa, a fuerza de compasión / Como quedaste en la vía y tu viejo, un pobre tano / Era chivo con los cosos pelandrunes como vos | F12: Lloró Como Una Mujer · Edmundo Rivero (1967) | G12: Mi mamá tomando merca, todo enfrente 'e mi cara (Fiumba) / Y mi viejo después de eso me echó fuera 'e la casa / Pero si no | H12: OPA · Dillom (2021) | I12: Tomas Borda | J12: falso_amigo | K12: A | L12: Se dice de la persona de edad | M12: Valentín Garfi | N12: falso_amigo | O12: A | P12: Mujer, persona del sexo femenino (coloq.; Bol. y Méx.) | Q12: =IF(OR(J12="",N12=""),"",IF(J12=N12,"sí","no")) | R12: =IF(OR(K12="",O12=""),"",IF(K12=O12,"sí","no"))
A13: CUR-012 | B13: macana | C13: Error, equivocación; cosa mal hecha. | D13: diccionarioargentino.com | E13: De envenenarse mi hermana / No hay bochinche ni macana / Que en tu homenaje no hiciera | F13: Apología del Tango · Tita Merello (1969) | G13: Rebota en la fuente / ¡Ay, qué macana! / Se posa en su frente | H13: La tortuga Uga · Flor Ansaldo (2020) | I13: Tomas Borda | J13: falso_amigo | K13: B | L13: f. Am. Garrote grueso. Hay vigilantes de barrio (muchachos adolescentes con macanas y tubos de fierro). [C]. | M13: Valentín Garfi | N13: polisemico_interno | O13: B | Q13: =IF(OR(J13="",N13=""),"",IF(J13=N13,"sí","no")) | R13: =IF(OR(K13="",O13=""),"",IF(K13=O13,"sí","no"))
A14: CUR-013 | B14: pico | C14: En Argentina, dícese que significa o representa, la accion humana de indole apareamental entre humanos, comunmente denominada "beso". | D14: diccionarioargentino.com | E14: Todo' los pibito' fumando del rico / Toda' esa' bandida' quieren darme un pico / Por allá el machimbre parece milico | F14: Tamo Chelo · El Noba (2021) | G14: Un bicho gordo como un salchichón / Dice “qué rico” y abriendo el pico / Pesca al perrito como un camarón | H14: El Show Del Perro Salchicha · María Elena Walsh (1966) | I14: Tomas Borda | J14: falso_amigo | K14: A | L14: Cima puntiaguda de una montaña | M14: Valentín Garfi | N14: falso_amigo | O14: A | P14: Colín de pan pequeño (Esp.) | Q14: =IF(OR(J14="",N14=""),"",IF(J14=N14,"sí","no")) | R14: =IF(OR(K14="",O14=""),"",IF(K14=O14,"sí","no"))
A15: CUR-014 | B15: cana | C15: Refiriéndose a la policia, a ir detenido a la comisaria o prisión. | D15: diccionarioargentino.com | E15: Que se nos cruza en la vida / Por vos he morfao más canas / Que pelos tengo en el mate | F15: Apología del Tango · Tita Merello (1969) | G15: Como me engrupiste vos / Está en cana, prontuariado / Como agente 'e la camorra | H15: Chorra · Edmundo Rivero (1959) | I15: Tomas Borda | J15: polisemico_interno | K15: B | M15: Valentín Garfi | N15: polisemico_interno | O15: B | Q15: =IF(OR(J15="",N15=""),"",IF(J15=N15,"sí","no")) | R15: =IF(OR(K15="",O15=""),"",IF(K15=O15,"sí","no")) | U15: Fragmento A usa el sentido literal (pelo canoso: "...más canas que pelos tengo en el mate"), no el rioplatense (policía/preso); por eso se eligió B.
A16: CUR-015 | B16: mango | C16: Sinónimo de dinero. | D16: diccionarioargentino.com | E16: De manguero doctorao / Y que un mango descubrís / Aunque lo hayan enterrao | F16: Dónde Hay Un Mango? · Tita Merello (1965) | G16: Cuando rajés los tamangos / Buscando este mango / Que te haga morfar | H16: Yira, Yira · Carlos Gardel (1930) | I16: Tomas Borda | J16: falso_amigo | K16: B | L16: Parte alargada, estrecha y con un extremo libre, por la que se puede agarrar un instrumento o utensilio | M16: Valentín Garfi | N16: falso_amigo | O16: B | P16: Persona guapa, atractiva (El Salv., Méx. y Nic.) | Q16: =IF(OR(J16="",N16=""),"",IF(J16=N16,"sí","no")) | R16: =IF(OR(K16="",O16=""),"",IF(K16=O16,"sí","no"))
A17: CUR-016 | B17: malevo | C17: Vulgar, propio del arrabal. | D17: Wikcionario | E17: Se dice de mí / Se dice que soy fiera, que camino a lo malevo / Que soy chueca y que me muevo con un aire compadrón | F17: Se Dice de Mí · Tita Merello (1955) | G17: Nacido en los suburbios / Malevos y turbios / Hoy | H17: Yo soy el tango · Miguel Caló | I17: Tomas Borda | J17: lunfardo_sin_homonimo | K17: A | M17: Valentín Garfi | N17: lunfardo_sin_homonimo | O17: A | Q17: =IF(OR(J17="",N17=""),"",IF(J17=N17,"sí","no")) | R17: =IF(OR(K17="",O17=""),"",IF(K17=O17,"sí","no"))
A18: CUR-017 | B18: gil | C18: Insulto a una persona que no cumple lo pautado o no tiene códigos | D18: diccionarioargentino.com | E18: En el amor yo solo sé / Que a más de un gil dejé de a pie / Podrán decir, podrán hablar | F18: Se Dice de Mí · Tita Merello (1955) | G18: ¡Lo que más bronca me da / Es haber estao' tan gil! / Si hace un mes me desayuno | H18: Chorra · Edmundo Rivero (1959) | I18: Tomas Borda | J18: lunfardo_sin_homonimo | K18: A | M18: Valentín Garfi | N18: lunfardo_sin_homonimo | O18: A | Q18: =IF(OR(J18="",N18=""),"",IF(J18=N18,"sí","no")) | R18: =IF(OR(K18="",O18=""),"",IF(K18=O18,"sí","no"))
A19: CUR-018 | B19: bailar | C19: Derrotar contundentemente. | D19: Wikcionario | E19: de aquí, cuántos de ellos aún están / Ahora mírame a mí, que te la puedo bailar / Solo elígeme el beat, el resto lo hace papá | F19: Vivimos Deprisa · Sofía Gabanna (2021) | I19: Tomas Borda | J19: polisemico_interno | K19: A | M19: Valentín Garfi | N19: polisemico_interno | O19: A | Q19: =IF(OR(J19="",N19=""),"",IF(J19=N19,"sí","no")) | R19: =IF(OR(K19="",O19=""),"",IF(K19=O19,"sí","no"))
A20: CUR-019 | B20: pobre | C20: Que tiene pocos bienes materiales. | D20: Wikcionario | E20: ahí que tenerla presente / Muchas te amarán siendo rico y pocas siendo pobre, fuck (Ey) / Si lo que yo hago yo no lo pueden hacer | F20: Nena · Zaramay (2018) | G20: Se van al sobre, yo no sobro (No sobro) / De pobre a rico como Rondo (Rondo) / Ya me conocen como el monstruo | H20: Hello Cotto · Duki (2017) | I20: Tomas Borda | J20: espanol_general | K20: A | M20: Valentín Garfi | N20: espanol_general | O20: A | Q20: =IF(OR(J20="",N20=""),"",IF(J20=N20,"sí","no")) | R20: =IF(OR(K20="",O20=""),"",IF(K20=O20,"sí","no"))
A21: CUR-020 | B21: cotorro | C21: Inmueble o habitación destinada para encuentros amorosos clandestinos. | D21: Wikcionario | E21: Agarrar lo que está hecho / El cotorro es el lugar / Donde se hace el amor | F21: Milonga Lunfarda · Edmundo Rivero (1972) | G21: Pa' olvidarme de tu amor / Cuando voy a mi cotorro / Y lo veo desarreglado | H21: Mi noche triste · Carlos Gardel (1917) | I21: Tomas Borda | J21: falso_amigo | K21: A | L21: adj. Méx. Dicho de una cosa: Bonita, atractiva, interesante. | M21: Valentín Garfi | N21: falso_amigo | O21: A | P21: Bonita, atractiva, interesante (adj., Méx.) | Q21: =IF(OR(J21="",N21=""),"",IF(J21=N21,"sí","no")) | R21: =IF(OR(K21="",O21=""),"",IF(K21=O21,"sí","no"))
A22: CUR-021 | B22: piola | C22: Adjetivo que califica a quien resuelve situaciones gracias a su ingenio; también algo que está bueno. | D22: diccionarioargentino.com | E22: Acá no se usa chupín, se viste ancho / No te hagas el piola, si en Varela sos un pancho / Si quiero te arrebato, no compro | F22: PICA · EL NOBA (2022) | G22: Estoy de gira por el barrio y mañana tengo fecha / Pero me porto piola, así la 12 no sospecha / (Fuck, try me) | H22: A$AP · Dillom (2019) | I22: Tomas Borda | J22: falso_amigo | K22: A | L22: f. Cuerda delgada. | M22: Valentín Garfi | N22: polisemico_interno | O22: A | Q22: =IF(OR(J22="",N22=""),"",IF(J22=N22,"sí","no")) | R22: =IF(OR(K22="",O22=""),"",IF(K22=O22,"sí","no"))
A23: CUR-022 | B23: curro | C23: Situación arreglada previamente, generalmente de manera injusta y/o inmoral. | D23: diccionarioargentino.com | E23: dealer' en lo' burro' (Uh) / Aprovechen el momento y saquen provecho al curro (Uh, uh-uh) / Ya tú sabe', canto envido (Ya lo dije con susurro) | F23: Freestyle Session #14 “LOS INTOCABLES” · Zaramay (2021) | G23: Sos cadenera, flor sin berretines / Que currás a los cuores con tu rango; / Pero el choma que aceita tus patines | H23: A Buenos Aires Lunfa · Edmundo Rivero (1967) | I23: Tomas Borda | J23: falso_amigo | K23: A | L23: m. coloq. trabajo (‖ acción de trabajar). | M23: Valentín Garfi | N23: falso_amigo | O23: A | P23: Trabajo o labor (uso cotidiano en España; el DLE no lo marca regionalmente) | Q23: =IF(OR(J23="",N23=""),"",IF(J23=N23,"sí","no")) | R23: =IF(OR(K23="",O23=""),"",IF(K23=O23,"sí","no"))
A24: CUR-023 | B24: pendejo | C24: 1 Usado para describir a alguien joven (Pendejo significa realmente pelo del pubis) 2 Usado a veces para describir a persona despectivamente a alguien medio tonto. | D24: diccionarioargentino.com | E24: El día que muera, moriré en mi ley, ah / Una pendeja egoísta, un poco masoquista / Su familia es cheta, sus papás son macristas | F24: Buenos tiempos · Dillom (2024) | G24: Me jode / Lejos del complejo de pendejos que la soben / Ven un lazo con el viejo rap, entonces no lo roben | H24: Oro Puro · 808god (2020) | I24: Tomas Borda | J24: falso_amigo | K24: A | L24: adj. coloq. Tonto, estúpido. Mex | M24: Valentín Garfi | N24: falso_amigo | O24: A | P24: Tonto, estúpido (muy asociado a México; el DLE no lo marca regionalmente) | Q24: =IF(OR(J24="",N24=""),"",IF(J24=N24,"sí","no")) | R24: =IF(OR(K24="",O24=""),"",IF(K24=O24,"sí","no"))
A25: CUR-024 | B25: guita | C25: Significa dinero, plata. | D25: diccionarioargentino.com | E25: Y al vivo le baten rana / La guita o el vento es / El dinero que circula | F25: Milonga Lunfarda · Edmundo Rivero (1972) | G25: fin de mes me dan miguitas para que no me queje / Puta, yo quiero mi guita, no escuchar boludeces / Estoy tan cansado de este sentimiento | H25: Mi peor enemigo · Dillom (2024) | I25: Tomas Borda | J25: lunfardo_sin_homonimo | K25: B | M25: Valentín Garfi | N25: lunfardo_sin_homonimo | O25: B | Q25: =IF(OR(J25="",N25=""),"",IF(J25=N25,"sí","no")) | R25: =IF(OR(K25="",O25=""),"",IF(K25=O25,"sí","no"))
A26: CUR-025 | B26: chabón | C26: Término coloquial para referirse a un chico o una chica. | D26: diccionarioargentino.com | E26: El chorro, un vulgar ladrón / Al zonzo, llaman chabón / Y al vivo le baten rana | F26: Milonga Lunfarda · Edmundo Rivero (1972) | G26: Ese cuerpo compadrón, algún... / Algún oscuro chabón / Será el llamado a cargarte | H26: En un feca · Edmundo Rivero (1975) | I26: Tomas Borda | J26: lunfardo_sin_homonimo | K26: A | M26: Valentín Garfi | N26: lunfardo_sin_homonimo | O26: A | Q26: =IF(OR(J26="",N26=""),"",IF(J26=N26,"sí","no")) | R26: =IF(OR(K26="",O26=""),"",IF(K26=O26,"sí","no"))
A27: CUR-026 | B27: viste | C27: Muletilla para confirmar que el interlocutor sigue el relato; equivale a «¿sabés?» o «¿entendés?». | D27: definición del grupo (no figura en Wikcionario ni en diccionarioargentino.com) | E27: Las tardecitas de Buenos Aires tiene ese qué sé yo, ¿viste? / Salís de tu casa por Arenales, lo de siempre en la calle y en | F27: Balada Para un Loco · Roberto Goyeneche (1969) | I27: Tomas Borda | J27: polisemico_interno | K27: A | M27: Valentín Garfi | N27: polisemico_interno | O27: A | Q27: =IF(OR(J27="",N27=""),"",IF(J27=N27,"sí","no")) | R27: =IF(OR(K27="",O27=""),"",IF(K27=O27,"sí","no")) | U27: Acepción rioplatense = muletilla confirmatoria; "viste" como forma verbal de "ver" es general en todo el español.
A28: CUR-027 | B28: flor | C28: Antepuesto a un sustantivo, indica que es grande o notable: flor de susto, flor de quilombo. | D28: definición del grupo (el sentido intensificador no figura en las tres fuentes del pipeline) | E28: te da también te quita / Que se hace la viva y está muerta la mosquita / Que parecía un duro y es un flor de mantequita | F28: Esa mierda · Sara Hebe (2012) | G28: La luz de todos los colores, cantando / El color de una piel y de una flor / Una guitarra y tu voz | H28: Estaré · Los Visitantes (1996) | I28: Tomas Borda | J28: polisemico_interno | K28: A | M28: Valentín Garfi | N28: polisemico_interno | O28: A | Q28: =IF(OR(J28="",N28=""),"",IF(J28=N28,"sí","no")) | R28: =IF(OR(K28="",O28=""),"",IF(K28=O28,"sí","no"))
A29: CUR-028 | B29: quilombo | C29: Forma de decir caos, desorden, pelea, un gran problema. | D29: diccionarioargentino.com | E29: que pega como Cotto / Soy de lo' pibes del fondo (Uh), de los adicto' al quilombo (Uh) / Mejor no ronquen con mi combo (Más na') | F29: Hello Cotto · Duki (2017) | G29: Estamos todos jugados, nada nos importa ya / Sigamos haciendo quilombo / La yuta no nos va llevar | H29: Los Pibes Chorros · Los Pibes Chorros (2001) | I29: Tomas Borda | J29: lunfardo_sin_homonimo | K29: A | M29: Valentín Garfi | N29: lunfardo_sin_homonimo | O29: A | Q29: =IF(OR(J29="",N29=""),"",IF(J29=N29,"sí","no")) | R29: =IF(OR(K29="",O29=""),"",IF(K29=O29,"sí","no"))
A30: CUR-029 | B30: jalar | C30: Inhalar con fines psicoactivos los vapores de un disolvente, generalmente colocándolo en una bolsa que se acerca a la boca y la nariz. | D30: Wikcionario | E30: Podés encontrarme por ahí, perdido sin Waze / Jalando popper con los gays / El día que muera, moriré en mi ley | F30: Buenos tiempos · Dillom (2024) | G30: Te busco x esos pasillos / Por ti jalo el gatillo / Que lo que tenga q pasar | H30: Quiero · Stefy Xipolitakis | I30: Tomas Borda | J30: falso_amigo | K30: A | L30: tr. coloq. Tirar de algo o de alguien. Esp | M30: Valentín Garfi | N30: polisemico_interno | O30: A | Q30: =IF(OR(J30="",N30=""),"",IF(J30=N30,"sí","no")) | R30: =IF(OR(K30="",O30=""),"",IF(K30=O30,"sí","no"))
A31: CUR-030 | B31: tesoro | C31: Depósito de plata, oro, y otros bienes de gran valor. | D31: Wikcionario | E31: Vamos a desembarcar / Muchos tesoros, joyas y perlas / Que ha conseguido ganar | F31: El Pirata Cara de Rata · Flor Ansaldo (2020) | G31: De tus ojos nunca quiero verme lejos / ¡Divinos tesoros de amor y de ensueño! / De tus ojos vivo | H31: Ruego · Felipe Boero | I31: Tomas Borda | J31: espanol_general | K31: B | M31: Valentín Garfi | N31: espanol_general | O31: B | Q31: =IF(OR(J31="",N31=""),"",IF(J31=N31,"sí","no")) | R31: =IF(OR(K31="",O31=""),"",IF(K31=O31,"sí","no"))
A32: CUR-031 | B32: capo | C32: Ser capo es ser muy bueno en algo, ser el mejor. | D32: diccionarioargentino.com | E32: quedo guapo si la ven conmigo, eh / Guapo eh, guapo, uh, sapo, soy el capo del hood / Tanto al mes, tanto flu', guapo, guapo, guapo | F32: Guapo · YSY A (2018) | G32: ¡Con sentimiento! / El Ruca, el Loco Ale y Toca, el capo de la villa / Re tirado y descontrolado, un pucho loco me estoy fumando | H32: Pucho Loco · Damas Gratis (2008) | I32: Tomas Borda | J32: polisemico_interno | K32: B | M32: Valentín Garfi | N32: polisemico_interno | O32: B | Q32: =IF(OR(J32="",N32=""),"",IF(J32=N32,"sí","no")) | R32: =IF(OR(K32="",O32=""),"",IF(K32=O32,"sí","no"))
A33: CUR-032 | B33: muerto | C33: Inhábil, sobre todo cuando refiere a juegos o deportes. | D33: Wikcionario | E33: nunca me quiso, y estoy loco por su beso / Mañana puedo estar muerto, como también estar preso / Si salgo de casa, no sabré si vo'a | F33: Freestyle Session #5 · Zaramay (2019) | G33: Ver fuerza salir del lodo / Watch me, ya muerta, pero escribiendo hits / I am confuse como Cuasimodo | H33: KAMIKAZE · Sofía Gabanna (2023) | I33: Tomas Borda | J33: polisemico_interno | K33: B | M33: Valentín Garfi | N33: polisemico_interno | O33: B | Q33: =IF(OR(J33="",N33=""),"",IF(J33=N33,"sí","no")) | R33: =IF(OR(K33="",O33=""),"",IF(K33=O33,"sí","no")) | U33: Ni A ni B reflejan claramente el sentido rioplatense de referencia (inhábil en juegos/deportes); ambos suenan al sentido literal. Revisar con Tomás.
A34: CUR-033 | B34: birra | C34: Forma de decirle a la cerveza. | D34: diccionarioargentino.com | E34: Acá siempre son 4:20, y estamo' de la cabeza, con simpleza / Birra barata y mala en lata, má' la planta santa esa / La que calma | F34: CANGURO · WOS (2019) | G34: se hace larga tengo que remar / Si es un día de calor unas birras tomar / Pero hay algo que me atrapa y no puedo escapar | H34: Lo Peor · Kumbia Queers (2015) | I34: Tomas Borda | J34: lunfardo_sin_homonimo | K34: A | M34: Valentín Garfi | N34: lunfardo_sin_homonimo | O34: A | Q34: =IF(OR(J34="",N34=""),"",IF(J34=N34,"sí","no")) | R34: =IF(OR(K34="",O34=""),"",IF(K34=O34,"sí","no"))
A35: CUR-034 | B35: vento | C35: Dinero, en especial en efectivo. | D35: Wikcionario | E35: Y al vivo le baten rana / La guita o el vento es / El dinero que circula | F35: Milonga Lunfarda · Edmundo Rivero (1972) | G35: 'Tam-tam-tamo' chelo / Mis ñeri' toman tussi en un Vento / De como terminamo', mejor no te cuento | H35: Tamo Chelo · El Noba (2021) | I35: Tomas Borda | J35: lunfardo_sin_homonimo | K35: A | M35: Valentín Garfi | N35: lunfardo_sin_homonimo | O35: A | Q35: =IF(OR(J35="",N35=""),"",IF(J35=N35,"sí","no")) | R35: =IF(OR(K35="",O35=""),"",IF(K35=O35,"sí","no"))
A36: CUR-035 | B36: fierro | C36: Arma de fuego. | D36: diccionarioargentino.com | E36: de usar tanga (Jaja) / Pa' pelea' el Luna Park, desde que hay fierro nadie e' langa / No pode' hablar de má' cuando hay dos ase' | F36: Freestyle Session #14 “LOS INTOCABLES” · Zaramay (2021) | G36: La mafia a tu banda la saca del vuelo / Y listo, llevo fierro cheto y chico / Porque .9 usan los milico' (Oh) | H36: Tamo Chelo (Remix) · EL NOBA (2022) | I36: Tomas Borda | J36: polisemico_interno | K36: A | M36: Valentín Garfi | N36: polisemico_interno | O36: A | Q36: =IF(OR(J36="",N36=""),"",IF(J36=N36,"sí","no")) | R36: =IF(OR(K36="",O36=""),"",IF(K36=O36,"sí","no"))
A37: CUR-036 | B37: turro | C37: Persona de mal proceder, de poca confianza. | D37: diccionarioargentino.com | E37: son más de lo mismo (Oh, oh) / Y que vos querés un turro que esté puesto pa' quererte / Y pa' sacarte de tu vida normal | F37: Mamichula · Trueno (2020) | G37: Pa' eso feka' tengo repelente / Yo no soy un turro, tengo el corazón valiente, yah / Yo soy del barrio desde que nací | H37: Azul y Oro · Trueno (2020) | I37: Tomas Borda | J37: lunfardo_sin_homonimo | K37: A | M37: Valentín Garfi | N37: lunfardo_sin_homonimo | O37: A | Q37: =IF(OR(J37="",N37=""),"",IF(J37=N37,"sí","no")) | R37: =IF(OR(K37="",O37=""),"",IF(K37=O37,"sí","no"))
A38: CUR-037 | B38: dormir | C38: Engañar a alguien para obtener un beneficio. | D38: Wikcionario | E38: Cuando pierda todas las partidas / Cuando duerma con la soledad / Cuando se me cierren las salidas | F38: Resistiré (Versión Reggaetón) · Zulma Lobato (2009) | G38: Turbulencia, aguamiel / El día se durmió / Aplazado al calor, pasionaria | H38: Alas de la Mañana · Lito Epumer (2004) | I38: Tomas Borda | J38: polisemico_interno | K38: A | M38: Valentín Garfi | N38: polisemico_interno | O38: A | Q38: =IF(OR(J38="",N38=""),"",IF(J38=N38,"sí","no")) | R38: =IF(OR(K38="",O38=""),"",IF(K38=O38,"sí","no")) | U38: Ni A ni B reflejan claramente el sentido rioplatense de referencia (engañar); ambos suenan al sentido literal. Revisar con Tomás.
A39: CUR-038 | B39: taco | C39: Parte posterior elevada del calzado. | D39: Wikcionario | E39: elegante hablando, lady, no hace falta un saco / Y a ti pa' ser mujer no te hacen falta tacos / Mis negro' experimentan con el amoniaco | F39: Nena · Zaramay (2018) | G39: Salta, bitch, jumpin' and jumpin' (Jumpin'), jumpin' / Bitch, now, la quiero en tacos, compitiendo como Elvira Hancock (Uh) / Que tengo mis puta' pero quiero a | H39: Elvira · 808God (2016) | I39: Tomas Borda | J39: falso_amigo | K39: A | L39: Tortilla de maíz enrollada con relleno, comida típica (Méx.) | M39: Valentín Garfi | N39: falso_amigo | O39: A | P39: Tortilla de maíz enrollada con relleno, comida típica (Méx.) | Q39: =IF(OR(J39="",N39=""),"",IF(J39=N39,"sí","no")) | R39: =IF(OR(K39="",O39=""),"",IF(K39=O39,"sí","no"))
A40: CUR-039 | B40: boludo | C40: Persona estupida, tonta, una persona imbecil | D40: diccionarioargentino.com | E40: a llevarte a lo profundo de mi mente / ¿Te pensás que soy boludo? ¿Que no sé cuándo me mienten? / Te pensás que yo no tengo | F40: Muñecas · Dillom (2024) | G40: Me la pone tan gorda que le hacen body-shaming / (Ay, same, boluda, yo también tengo ascendente en sagitario, | H40: Buenos tiempos · Dillom (2024) | I40: Tomas Borda | J40: falso_amigo | K40: B | L40: adj. Méx. Que tiene protuberancias. | M40: Valentín Garfi | N40: falso_amigo | O40: B | P40: Que tiene bultos o protuberancias (Méx.) | Q40: =IF(OR(J40="",N40=""),"",IF(J40=N40,"sí","no")) | R40: =IF(OR(K40="",O40=""),"",IF(K40=O40,"sí","no"))
A41: CUR-040 | B41: mate | C41: Bebida con yerba, tradicional de Argentina. CÓMO NO VAS A SABER QUÉ ES UN MATE?! xd | D41: diccionarioargentino.com | E41: Por vos he morfao más canas / Que pelos tengo en el mate / Por vos hizo el disparate | F41: Apología del Tango · Tita Merello (1969) | G41: Siempre traigo bizcochitos / Pa' tomar con matecito / Como si estuvieras vos | H41: Mi noche triste · Carlos Gardel (1917) | I41: Tomas Borda | J41: polisemico_interno | K41: B | M41: Valentín Garfi | N41: polisemico_interno | O41: B | Q41: =IF(OR(J41="",N41=""),"",IF(J41=N41,"sí","no")) | R41: =IF(OR(K41="",O41=""),"",IF(K41=O41,"sí","no")) | U41: Al menos 3 acepciones usadas acá: la bebida, jaque mate (ajedrez), y "cabeza" (coloq.).
A42: CUR-041 | B42: cargar | C42: Tomarle el pelo a alguien. | D42: diccionarioargentino.com | E42: Me puse a pensar si vale la pena / Cargar esa cruz por ti, por mí / Dame una señal | F42: Cuero 皮膚 · Yesan 雪山 (2023) | G42: Hicimos del ruido las respuestas / Caminamos los desposeídos cargando los mantos que cubrirán sus cuerpos | H42: Pedagogía de la venganza · Cienfuegos (2021) | I42: Tomas Borda | J42: polisemico_interno | M42: Valentín Garfi | N42: polisemico_interno | Q42: =IF(OR(J42="",N42=""),"",IF(J42=N42,"sí","no")) | R42: =IF(OR(K42="",O42=""),"",IF(K42=O42,"sí","no")) | U42: Ninguno de los dos fragmentos (A ni B) refleja el sentido de referencia (burlarse/tomar el pelo); ambos usan "cargar" en sentido literal de peso. Fragmento sin elegir, revisar con Tomás o posible reemplazo.
A43: CUR-042 | B43: blanca | C43: Principio activo de la coca extraído en forma de clorhidrato, usado como medicamento y en especial como droga recreativa. | D43: Wikcionario | E43: Una guitarra y tu voz / La blanca y cálida luz / Del sol | F43: Estaré · Los Visitantes (1996) | G43: Conocí una cheta con la piel naranja / Ella tomaba keta y yo tomaba blanca / Me dijo que se drogaba una vez cada tanto | H43: Buenos tiempos · Dillom (2024) | I43: Tomas Borda | J43: polisemico_interno | K43: B | M43: Valentín Garfi | N43: polisemico_interno | O43: B | Q43: =IF(OR(J43="",N43=""),"",IF(J43=N43,"sí","no")) | R43: =IF(OR(K43="",O43=""),"",IF(K43=O43,"sí","no"))
A44: CUR-043 | B44: raro | C44: Que no es corriente, que es diferente a lo común en su clase. | D44: Wikcionario | E44: Algunas personas no saben de lo que yo hablo / Dicen que esto es raro y eso es un halago / Dicen que esto es | F44: No Hay Rencor · Sofía Gabanna (2019) | G44: es que te molesta (Wow, yeah) / Sé que a veces soy muy raro y no te doy respuesta, huh (Skrrt) / Pero estás enamora', tu cara | H44: iPhone · Zell (2024) | I44: Tomas Borda | J44: espanol_general | K44: A | M44: Valentín Garfi | N44: espanol_general | O44: A | Q44: =IF(OR(J44="",N44=""),"",IF(J44=N44,"sí","no")) | R44: =IF(OR(K44="",O44=""),"",IF(K44=O44,"sí","no"))
A45: CUR-044 | B45: porteño | C45: Proveniente del puerto de Buenos Aires. Hace mucho tiempo atrás, la ciudad de Buenos aires era la única en tener puerto para sida de barco en el país , entonces quienes vivían allí eran "porteños ". Este término se sigue utilizando hasta hoy en día. | D45: diccionarioargentino.com | E45: Que tengo para vos / Loco, loco, loco, cuando anochezca en tu porteña soledad / Por la ribera de tu sabana vendré con un poema y un | F45: Balada Para un Loco · Roberto Goyeneche (1969) | G45: Llevo un sello de nobleza / Soy porteña de una pieza / Tengo voz de bandoneón | H45: Arrabalera · Tita Merello (1955) | I45: Tomas Borda | J45: espanol_general | K45: B | M45: Valentín Garfi | N45: espanol_general | O45: B | Q45: =IF(OR(J45="",N45=""),"",IF(J45=N45,"sí","no")) | R45: =IF(OR(K45="",O45=""),"",IF(K45=O45,"sí","no"))
A46: CUR-045 | B46: pinta | C46: ''pinta'' o se usa cuando le preguntás a alguien qué tiene ganas de hacer algo, o cuando le preguntás si está de acuerdo en hacer lo que vos querés. | D46: diccionarioargentino.com | E46: Y me pongo loco, re loco, re loco / Si pinta un mellizo ella le da hasta el piso / Se va de caravana y nunca le | F46: Piloto · EL NOBA (2022) | G46: bien ahí al ritmo. ¿Cómo e'? 'tamo acá con el Maxi, si pinta, despué' a la noche o más tarde nos cruzamo' ahí pa' pega' | H46: Freestyle Session #14 “LOS INTOCABLES” · Zaramay (2021) | I46: Tomas Borda | J46: polisemico_interno | K46: B | M46: Valentín Garfi | N46: polisemico_interno | O46: B | Q46: =IF(OR(J46="",N46=""),"",IF(J46=N46,"sí","no")) | R46: =IF(OR(K46="",O46=""),"",IF(K46=O46,"sí","no"))
A47: CUR-046 | B47: junar | C47: Sinónimo de conocer, reconocer, ser conocido. | D47: diccionarioargentino.com | E47: re del after / Y el telo paga la vuelta, y no te juno en la del Master / Me escuchan los pibito' que andan en chapa | F47: Del Año · EL NOBA (2021) | G47: También daba clases de hombría de bien; / Junaba de noches y de madrugadas / Piloteaba aviones y más de un beguén | H47: A lo Megata · Edmundo Rivero (1982) | I47: Tomas Borda | J47: lunfardo_sin_homonimo | K47: A | M47: Valentín Garfi | N47: lunfardo_sin_homonimo | O47: A | Q47: =IF(OR(J47="",N47=""),"",IF(J47=N47,"sí","no")) | R47: =IF(OR(K47="",O47=""),"",IF(K47=O47,"sí","no"))
A48: CUR-047 | B48: logi | C48: Persona tonta, estúpida, aburrida. Sinónimo de Gil. | D48: diccionarioargentino.com | E48: Todo' lo' podere' corte Kakaroto / Logi, no te peine', no salí' en la foto / Ayer vino tu guacha, era mi copiloto | F48: KAKAROTO · El Noba | I48: Tomas Borda | J48: lunfardo_sin_homonimo | K48: A | M48: Valentín Garfi | N48: lunfardo_sin_homonimo | O48: A | Q48: =IF(OR(J48="",N48=""),"",IF(J48=N48,"sí","no")) | R48: =IF(OR(K48="",O48=""),"",IF(K48=O48,"sí","no"))
A49: CUR-048 | B49: boliche | C49: Es el lugar donde se suele ir a bailar; en otros países se conoce como discoteca. | D49: diccionarioargentino.com | E49: gusta cuando tú te me sigue' (Sí) / Te ponen música en el boliche y te la vive' (Uh-uh) / Cumbia con reggaetón, un perreo 'e salón | F49: Tamo Chelo (Remix) · EL NOBA (2022) | G49: No puedo sacarla de mi mente en toda la semana / Hace cuatro meses que yo vengo a este boliche / Para verte bailar entre la gente | H49: Daniela · Kumbia Queers (2010) | I49: Tomas Borda | J49: falso_amigo | K49: A | L49: Bolera, lugar para jugar al boliche/bowling (Méx.) | M49: Valentín Garfi | N49: falso_amigo | O49: A | P49: Bolera, lugar para jugar al boliche/bowling (Méx.) | Q49: =IF(OR(J49="",N49=""),"",IF(J49=N49,"sí","no")) | R49: =IF(OR(K49="",O49=""),"",IF(K49=O49,"sí","no"))
A50: CUR-049 | B50: rajar | C50: utilizado en situaciones en las cuales debes irte muy rapido, inmediatamente porque tenes alguna obligacion, porque te mandaste alguna cagada, etc. | D50: diccionarioargentino.com | E50: Y apoliyar es dormirse / Rajar o piantarse es irse / Y esto lo manya cualquiera | F50: Milonga Lunfarda · Edmundo Rivero (1972) | G50: Si los cacha, los da vuelta / No les da tiempo a rajar / ¡Lo que más bronca me da | H50: Chorra · Edmundo Rivero (1959) | I50: Tomas Borda | J50: falso_amigo | K50: B | L50: tr. Dividir en rajas. | M50: Valentín Garfi | N50: falso_amigo | O50: B | P50: Hablar mal de alguien, desacreditarlo (Méx., entre otros) | Q50: =IF(OR(J50="",N50=""),"",IF(J50=N50,"sí","no")) | R50: =IF(OR(K50="",O50=""),"",IF(K50=O50,"sí","no"))
A51: CUR-050 | B51: cien | C51: Signo o signos usados para representar al número que tiene cien unidades. | D51: Wikcionario | E51: Quiero despertar y estar contigo de viaje / Y que los billetes de cien dolares caigan del traje / La nena quiere una Ferrari de carruaje (Ey) | F51: Nena · Zaramay (2018) | G51: Sé frontear, pero no exagero / Llegué a cien, vine desde cero / Dólare' desde el extranjero | H51: GIVENCHY · Duki (2022) | I51: Tomas Borda | J51: espanol_general | K51: B | M51: Valentín Garfi | N51: espanol_general | O51: B | Q51: =IF(OR(J51="",N51=""),"",IF(J51=N51,"sí","no")) | R51: =IF(OR(K51="",O51=""),"",IF(K51=O51,"sí","no"))
A52: CUR-051 | B52: boca | C52: Abertura anterior del tubo digestivo de los animales, por el cual se ingieren los alimentos. | D52: Wikcionario | E52: Pero si un mirar me hiere al pasar / Su boca de fuego, otra vez, quiero besar / Basta de carreras, se acabó la timba | F52: Por Una Cabeza · Carlos Gardel (1935) | G52: Leguisamo, mi nariz es puntiaguda / La figura no me ayuda y mi boca es un buzón / Si charlo con Luis, con Pedro o con Juan | H52: Se Dice de Mí · Tita Merello (1955) | I52: Tomas Borda | J52: espanol_general | K52: B | M52: Valentín Garfi | N52: espanol_general | O52: B | Q52: =IF(OR(J52="",N52=""),"",IF(J52=N52,"sí","no")) | R52: =IF(OR(K52="",O52=""),"",IF(K52=O52,"sí","no"))
A53: CUR-052 | B53: percanta | C53: Mujer o mina, puede que se use con connotacion negativa | D53: diccionarioargentino.com | E53: Letra de "Mi Noche Triste" / Percanta que me amuraste / En lo mejor de mi vida | F53: Mi noche triste · Carlos Gardel (1917) | G53: Mi noche triste alumbrar / Percanta que me amuraste / En lo mejor de mi vida | H53: Mi noche triste · Carlos Gardel (1917) | I53: Tomas Borda | J53: lunfardo_sin_homonimo | K53: A | M53: Valentín Garfi | N53: lunfardo_sin_homonimo | O53: A | Q53: =IF(OR(J53="",N53=""),"",IF(J53=N53,"sí","no")) | R53: =IF(OR(K53="",O53=""),"",IF(K53=O53,"sí","no"))
A54: CUR-053 | B54: paciencia | C54: Calma en la realización de alguna actividad. | D54: Wikcionario | E54: Se tragaron, vos, la “viuda” y el “guerrero” / Lo que me costó diez años de paciencia y de yugar / ¡Chorros!... | F54: Chorra · Edmundo Rivero (1959) | G54: Vieja no me va a querer; / En Europa y con paciencia / Me podrán embellecer" | H54: Manuelita La Tortuga · María Elena Walsh (1964) | I54: Tomas Borda | J54: espanol_general | K54: A | M54: Valentín Garfi | N54: espanol_general | O54: A | Q54: =IF(OR(J54="",N54=""),"",IF(J54=N54,"sí","no")) | R54: =IF(OR(K54="",O54=""),"",IF(K54=O54,"sí","no"))
A55: CUR-054 | B55: pelar | C55: Dejar pelado a alguien, gastar o quitar todo el dinero. | D55: Wikcionario | E55: Malandrín y estafador / Entre todos me pelaron con la cero / Tu silueta fue el anzuelo, donde yo me fui a ensartar | F55: Chorra · Edmundo Rivero (1959) | G55: porque su vida no es interesante (Ey) / Pa' tomar una Coca antes pelábamos el cobre / Y ahora por nuestra coca mandan el dinero en sobre | H55: Nena · Zaramay (2018) | I55: Tomas Borda | J55: falso_amigo | L55: prnl. Méx. Irse, escapar, huir precipitadamente. | M55: Valentín Garfi | N55: falso_amigo | P55: Irse/escapar precipitadamente, o morir (Méx., El Salv.) | Q55: =IF(OR(J55="",N55=""),"",IF(J55=N55,"sí","no")) | R55: =IF(OR(K55="",O55=""),"",IF(K55=O55,"sí","no")) | U55: Ninguno de los dos fragmentos refleja con claridad "sacar plata a alguien"; A es ambiguo (posible arma) y B es sobre pelar cables de cobre, literal. Fragmento sin elegir, revisar con Tomás o posible reemplazo.
A56: CUR-055 | B56: vacío | C56: Corte de carne tomado del vientre del vacuno, desde la parte posterior de la última costilla hasta la articulación del anca. Es una carne magra y tierna, empleada con frecuencia para el asado. | D56: Wikcionario | E56: Es para valientes que van por más! / El vacío que llevamos se agranda / Dentro de nuestro interior | F56: El Manual De Las Derrotas · Carajo (2019) | G56: en esta vida se me ha complicado (Oh-oh-oh) / Por eso me siento vacío y un poco frustrado (Oh-oh-oh) / Me siento mal, ya no sé ni | H56: U.S.A · LiL CaKe (2020) | I56: Tomas Borda | J56: polisemico_interno | M56: Valentín Garfi | N56: polisemico_interno | Q56: =IF(OR(J56="",N56=""),"",IF(J56=N56,"sí","no")) | R56: =IF(OR(K56="",O56=""),"",IF(K56=O56,"sí","no")) | U56: Ninguno de los dos fragmentos usa el sentido de referencia (corte de carne); ambos son el sentido figurado de "vacío emocional". Fragmento sin elegir, revisar con Tomás o posible reemplazo.
A57: CUR-056 | B57: mina | C57: Mujer, chica. | D57: diccionarioargentino.com | E57: en un 'pernó' mezclo a Paris con Puente Alsina / Fuiste compadre del botón y de la mina / Y hasta comadre del gavión y la pebeta | F57: El Choclo · Tita Merello (1954) | G57: El dolor de unas cadenas que me queman las muñecas / Y una mina que arrodilla mis arrestos de varón / Yo quiero morir conmigo | H57: Como Abrazo a un Rencor · Edmundo Rivero (1967) | I57: Tomas Borda | J57: polisemico_interno | K57: A | M57: Valentín Garfi | N57: polisemico_interno | O57: A | Q57: =IF(OR(J57="",N57=""),"",IF(J57=N57,"sí","no")) | R57: =IF(OR(K57="",O57=""),"",IF(K57=O57,"sí","no"))
A58: CUR-057 | B58: curtir | C58: Gustar de algo o alguien, tener preferencia por determinada cosa, comportamiento o hábito. | D58: diccionarioargentino.com | E58: cheta con money y cocaine / Me invitan un tiro y yo que las deliro, me voy a curtir a las diez / Tengan veinte o dieciséis | F58: Guapo · YSY A (2018) | G58: contando lo que yo viví (-ví) / Fuck tu film, los pi' no curtimos esa ni ahí / Pueden rimar, pa', pero no ser na' más pa' | H58: Crow · Acru (2018) | I58: Tomas Borda | J58: polisemico_interno | K58: B | M58: Valentín Garfi | N58: polisemico_interno | O58: B | Q58: =IF(OR(J58="",N58=""),"",IF(J58=N58,"sí","no")) | R58: =IF(OR(K58="",O58=""),"",IF(K58=O58,"sí","no"))
A59: CUR-058 | B59: fumar | C59: Coloq. Véase soportar, aguantar | D59: diccionarioargentino.com | E59: gente habla de más, solo es porque responde el vivo / ¿De que fumo mucho porro?, ¿que me gusta el efectivo? / Todo bien, pero ustedes siguen | F59: Freestyle Session #5 · Zaramay (2019) | G59: Yo te quiero corazon y no te tengo rencor / Fumo del malo y del bueno / Veo pasar el tiempo soñando lo que quiero | H59: Plantala · Kumbia Queers (2015) | I59: Tomas Borda | J59: polisemico_interno | M59: Valentín Garfi | N59: polisemico_interno | Q59: =IF(OR(J59="",N59=""),"",IF(J59=N59,"sí","no")) | R59: =IF(OR(K59="",O59=""),"",IF(K59=O59,"sí","no")) | U59: Ninguno de los dos fragmentos refleja el sentido de referencia (aguantar/soportar); ambos usan "fumar" literalmente (cigarrillo/porro). Fragmento sin elegir, revisar con Tomás o posible reemplazo.
A60: CUR-059 | B60: careta | C60: Persona hipócrita, falsa, doble cara. | D60: diccionarioargentino.com | E60: Acá la que más cobra suele ser la mas barata / Y siempre hay un careta que transa con una rata / ¡Basta, pará! No quiero hacerlo | F60: Esa mierda · Sara Hebe (2012) | G60: Porque al primero que se haga el ortiba / Por pancho y careta le vamos a dar / ''Mamá Chorra, tenes razón'' | H60: Llegamos los Pibes Chorros · Los Pibes Chorros (2002) | I60: Tomas Borda | J60: polisemico_interno | K60: B | M60: Valentín Garfi | N60: polisemico_interno | O60: B | Q60: =IF(OR(J60="",N60=""),"",IF(J60=N60,"sí","no")) | R60: =IF(OR(K60="",O60=""),"",IF(K60=O60,"sí","no"))
A61: CUR-060 | B61: cero | C61: Nombre del número 0. | D61: Wikcionario | E61: Malandrín y estafador / Entre todos me pelaron con la cero / Tu silueta fue el anzuelo, donde yo me fui a ensartar | F61: Chorra · Edmundo Rivero (1959) | G61: Sé frontear, pero no exagero / Llegué a cien, vine desde cero / Dólare' desde el extranjero | H61: GIVENCHY · Duki (2022) | I61: Tomas Borda | J61: espanol_general | K61: B | M61: Valentín Garfi | N61: espanol_general | O61: B | Q61: =IF(OR(J61="",N61=""),"",IF(J61=N61,"sí","no")) | R61: =IF(OR(K61="",O61=""),"",IF(K61=O61,"sí","no"))
A62: CUR-061 | B62: labio | C62: Parte del cuerpo que se parece a un labio₁, como el borde de una herida o las partes de los órganos genitales. | D62: Wikcionario | E62: Que la tierra pidió / Labios, sed, cautividad / Mar, vendimia, gravedad | F62: Alas de la Mañana · Lito Epumer (2004) | G62: tu lengua es de serpiente / Tu piel es la más suave y tus labios son crujientes / Si fueras una escort, yo sería tu mejor cliente | H62: Muñecas · Dillom (2024) | I62: Tomas Borda | J62: espanol_general | K62: A | M62: Valentín Garfi | N62: espanol_general | O62: A | Q62: =IF(OR(J62="",N62=""),"",IF(J62=N62,"sí","no")) | R62: =IF(OR(K62="",O62=""),"",IF(K62=O62,"sí","no"))
A63: CUR-062 | B63: remera | C63: Prenda de vestir que cubre el torso, de mangas cortas; camiseta. | D63: diccionarioargentino.com | E63: Usa siempre el mismo pantalón / Y una remera de los Rolling Stones, la colorada / Está buena por delante y por detrás | F63: La colorada · Los Pibes Chorros (2003) | G63: De una ola que no para de crecer / Hoy su cara está en todas las remeras / Es un muerto que no para de nacer | H63: Murguita del sur · Bersuit Vergarabat (1998) | I63: Tomas Borda | J63: lunfardo_sin_homonimo | K63: A | M63: Valentín Garfi | N63: lunfardo_sin_homonimo | O63: A | Q63: =IF(OR(J63="",N63=""),"",IF(J63=N63,"sí","no")) | R63: =IF(OR(K63="",O63=""),"",IF(K63=O63,"sí","no"))
A64: CUR-063 | B64: trap | C64: Subgénero del Rap. | D64: diccionarioargentino.com | E64: Porque sé que mañana con Agustín cenas / Lo mismo dije con el trap, me comeré la escena (Ey) / No le temo a la muerte, tengo | F64: Nena · Zaramay (2018) | G64: ahora hay tantas mujere' que por la noche me llaman / Esto del trap me incomoda porque toda' me la maman / Yo arriba y tú de | H64: Oye Baby · Zaramay (2020) | I64: Tomas Borda | J64: espanol_general | K64: B | M64: Valentín Garfi | N64: espanol_general | O64: B | Q64: =IF(OR(J64="",N64=""),"",IF(J64=N64,"sí","no")) | R64: =IF(OR(K64="",O64=""),"",IF(K64=O64,"sí","no")) | U64: Nombre del género musical, préstamo del inglés usado igual en todos los dialectos; no tiene carga rioplatense.
A65: CUR-064 | B65: chorro | C65: Persona que ha robado, ladron, delincuente | D65: diccionarioargentino.com | E65: Lo que me costó diez años de paciencia y de yugar / ¡Chorros!... / Vos, tu vieja y tu papá | F65: Chorra · Edmundo Rivero (1959) | G65: El que roba es el que afana / El chorro, un vulgar ladrón / Al zonzo, llaman chabón | H65: Milonga Lunfarda · Edmundo Rivero (1972) | I65: Tomas Borda | J65: polisemico_interno | K65: A | M65: Valentín Garfi | N65: polisemico_interno | O65: A | Q65: =IF(OR(J65="",N65=""),"",IF(J65=N65,"sí","no")) | R65: =IF(OR(K65="",O65=""),"",IF(K65=O65,"sí","no"))
A66: CUR-065 | B66: reír | C66: Reírse (emitir sonidos de alegría con la boca). | D66: Wikcionario | E66: Acaricia mi ensueño, el suave murmullo de tu suspirar / Como ríe la vida si tus ojos negros me quieren mirar / Y si es mío el | F66: El Dia Que Me Quieras · Carlos Gardel (1934) | G66: Y una banderita de taxi libre levantada en cada mano / Te reís, pero solo vos me ves / Porque los maniquíes me guiñan, los semáforos me | H66: Balada Para un Loco · Roberto Goyeneche (1969) | I66: Tomas Borda | J66: espanol_general | K66: B | M66: Valentín Garfi | N66: espanol_general | O66: B | Q66: =IF(OR(J66="",N66=""),"",IF(J66=N66,"sí","no")) | R66: =IF(OR(K66="",O66=""),"",IF(K66=O66,"sí","no"))
A67: CUR-066 | B67: faso | C67: Sinónimo de cigarrillo, puede ser de marihuana o de tabaco indistintamente. | D67: diccionarioargentino.com | E67: a dos casas de mi puntero / Por eso cuando voy a comprar faso la veo / Ella me dice: "Chico, invitáme a fumar que ese es | F67: Una Vela · Intoxicados (2003) | G67: El recuerdo de tu voz que me decía: / "Largá el faso, las pastillas y el alcohol" / Sin embargo, yo seguí dándole duro | H67: Sentimiento villero · Los Pibes Chorros (2001) | I67: Tomas Borda | J67: lunfardo_sin_homonimo | K67: B | M67: Valentín Garfi | N67: lunfardo_sin_homonimo | O67: B | Q67: =IF(OR(J67="",N67=""),"",IF(J67=N67,"sí","no")) | R67: =IF(OR(K67="",O67=""),"",IF(K67=O67,"sí","no"))
A68: CUR-067 | B68: plato | C68: Situación o persona divertida y alegre. | D68: Wikcionario | E68: Donde el pichón se cansó de esperar / Pone en el plato liebre por gato / Cosa que a todos nos puede pasar | F68: El Show Del Perro Salchicha · María Elena Walsh (1966) | G68: contrato' (Poh, poh) / Los fanes son los que van a llenar el plato / Y si no estoy contigo, el que te haga sufrir lo mato | H68: Nena · Zaramay (2018) | I68: Tomas Borda | J68: polisemico_interno | M68: Valentín Garfi | N68: polisemico_interno | Q68: =IF(OR(J68="",N68=""),"",IF(J68=N68,"sí","no")) | R68: =IF(OR(K68="",O68=""),"",IF(K68=O68,"sí","no")) | U68: Ni A ni B reflejan "situación/persona divertida" con claridad (A es el modismo "dar gato por liebre" = engañar; B es un modismo de recaudación). Candidato a reemplazo: re-correr pipeline/stage03b_contextos.py apuntado a este término con tope más alto.
A69: CUR-068 | B69: quemar | C69: Delatar a una persona o hacerla objeto de burla. Una persona también puede «quemarse» a sí misma. | D69: diccionarioargentino.com | E69: Que al jurar sonriendo, el amor que está mintiendo / Quema en una hoguera todo mi querer / Por una cabeza | F69: Por Una Cabeza · Carlos Gardel (1935) | G69: mi avenida (-nida) / Casi que la veo desde el balcón mientra' estoy quemando porquería / ¿Que quién me creo que soy? El mejor al meno' en | H69: Rockstar · Duki (2017) | I69: Tomas Borda | J69: polisemico_interno | M69: Valentín Garfi | N69: falso_amigo | P69: Desacreditar (El Salv. y Méx.) | Q69: =IF(OR(J69="",N69=""),"",IF(J69=N69,"sí","no")) | R69: =IF(OR(K69="",O69=""),"",IF(K69=O69,"sí","no")) | U69: B suena a "fumar algo" más que a "delatar/burlar", que es la acepción de referencia. Candidato a reemplazo, re-correr el pipeline para este término.
A70: CUR-069 | B70: ruido | C70: Sonido, en especial el que es fuerte y desagradable. | D70: Wikcionario | E70: Encerrado en mi cuarto y afuera llovía fuerte / Escuché un ruido fuerte y fui a fijarme / Subí a la terraza y vos estabas por tirarte, | F70: Últimamente · Dillom (2024) | G70: invité a salir / Vamos a la fiesta de un amigo, hay mucho escabio y mucho ruido / Un chabón me deliró y un roscazo se comió | H70: Qué mala suerte! · 2 Minutos (1994) | I70: Tomas Borda | J70: espanol_general | K70: B | M70: Valentín Garfi | N70: espanol_general | O70: B | Q70: =IF(OR(J70="",N70=""),"",IF(J70=N70,"sí","no")) | R70: =IF(OR(K70="",O70=""),"",IF(K70=O70,"sí","no"))
A71: CUR-070 | B71: yuta | C71: De origen lunfardo, quiere decir policía. | D71: diccionarioargentino.com | E71: Se creen dueños, salgan del medio, lo digo en serio / Fuera la yuta que meten al barrio, le tira a los pibe' y le mata | F71: CANGURO · WOS (2019) | G71: Descarten los tubos, empiecen a correr / La yuta esta muy cerca, no da para correr / El oficial grita, "¡Contra la pared! | H71: Demasiado tarde (La marcha) · 2 Minutos (1994) | I71: Tomas Borda | J71: lunfardo_sin_homonimo | K71: B | M71: Valentín Garfi | N71: lunfardo_sin_homonimo | O71: B | Q71: =IF(OR(J71="",N71=""),"",IF(J71=N71,"sí","no")) | R71: =IF(OR(K71="",O71=""),"",IF(K71=O71,"sí","no"))
A72: CUR-071 | B72: catrera | C72: Cama plegable con armazón de tijera. | D72: Wikcionario | E72: Que hace la vida fulera / La cama es una catrera / Y apoliyar es dormirse | F72: Milonga Lunfarda · Edmundo Rivero (1972) | G72: Como si estuvieras vos / Y si vieras la catrera / Como se pone cabrera | H72: Mi noche triste · Carlos Gardel (1917) | I72: Tomas Borda | J72: lunfardo_sin_homonimo | K72: B | M72: Valentín Garfi | N72: lunfardo_sin_homonimo | O72: B | Q72: =IF(OR(J72="",N72=""),"",IF(J72=N72,"sí","no")) | R72: =IF(OR(K72="",O72=""),"",IF(K72=O72,"sí","no"))
A73: CUR-072 | B73: sal | C73: Dicho de algo, que es de alto costo, caro, de precio alto. | D73: diccionarioargentino.com | E73: Muy lejos del sol, que quema de amor / Te doy pan, quieres sal / Nena, nunca te voy a dar lo que me pides | F73: Seminare · David Lebón (2018) | G73: Y es igual a las guirnaldas / Y es que este día es algo de sal / Me dejó vibrando al nacer | H73: Canción Para los Días de la Vida · María Gabriela Epumer (2000) | I73: Tomas Borda | J73: espanol_general | M73: Valentín Garfi | N73: polisemico_interno | Q73: =IF(OR(J73="",N73=""),"",IF(J73=N73,"sí","no")) | R73: =IF(OR(K73="",O73=""),"",IF(K73=O73,"sí","no")) | U73: Ninguno de los dos fragmentos usa claramente el sentido "caro/costoso". Candidato a reemplazo, re-correr el pipeline para este término.
A74: CUR-073 | B74: pucho | C74: Forma en que se les dice a los cigarrillos. | D74: diccionarioargentino.com | E74: (Este es el balneario de los doctores) / Ni del pucho que se fuma, ni la lámpara que cuelga / (Este es el balneario de los doctores | F74: El Balneario de los Doctores Crotos · Los Piojos (1998) | G74: Re tirado y descontrolado, un pucho loco me estoy fumando / Estoy sangrando y no tengo miedo ya de morir | H74: Pucho Loco · Damas Gratis (2008) | I74: Tomas Borda | J74: polisemico_interno | K74: A | M74: Valentín Garfi | N74: polisemico_interno | O74: A | Q74: =IF(OR(J74="",N74=""),"",IF(J74=N74,"sí","no")) | R74: =IF(OR(K74="",O74=""),"",IF(K74=O74,"sí","no"))
A75: CUR-074 | B75: joder | C75: En argentina usamos joder como sinonimo de molestar o un fastidio | D75: diccionarioargentino.com | E75: Todo' saben la' consecuencia' de jugar con lo' metal' / Si me joden al pana te hago dos por uno en funeral (¿Oíste?) / Empecé escribiendo pa' | F75: Oye Baby · Zaramay (2020) | G75: Tienen el mundo enfrente a sus ojos y no lo ven / Me jode / Lejos del complejo de pendejos que la soben | H75: Oro Puro · 808god (2020) | I75: Tomas Borda | J75: falso_amigo | K75: A | L75: intr. malson. Practicar el coito. | M75: Valentín Garfi | N75: polisemico_interno | O75: A | Q75: =IF(OR(J75="",N75=""),"",IF(J75=N75,"sí","no")) | R75: =IF(OR(K75="",O75=""),"",IF(K75=O75,"sí","no"))
A76: CUR-075 | B76: trucho | C76: si se refiere a un objeto, significa que es falso, de mala calidad, copiado, con algún desperfecto o algo que anda mal | D76: diccionarioargentino.com | E76: gusta que no pregunten mucho / Que estén buscando amor pero ese amor del trucho / Que sepan que el dolor y el placer es tan efímero | F76: Flores & Bombones · Yesan 雪山 (2025) | I76: Tomas Borda | J76: lunfardo_sin_homonimo | K76: A | M76: Valentín Garfi | N76: lunfardo_sin_homonimo | O76: A | Q76: =IF(OR(J76="",N76=""),"",IF(J76=N76,"sí","no")) | R76: =IF(OR(K76="",O76=""),"",IF(K76=O76,"sí","no"))
A77: CUR-076 | B77: duro | C77: Estar muy drogado | D77: diccionarioargentino.com | E77: Cabrones, dejen su mensaje ya, después de la señal / La vida es dura, y es común tener que enterrar a un abuelo / Pero no levantar | F77: Freestyle Session #5 · Zaramay (2019) | G77: Fría la noche como duro el pisar / La encontraron bajo un árbol aquí atrás | H77: Georgia Lee · Roxana Amed | I77: Tomas Borda | J77: falso_amigo | L77: m. Esp. Moneda de cinco pesetas. | M77: Valentín Garfi | N77: falso_amigo | P77: Moneda de cinco pesetas, ya desaparecida (Esp.) | Q77: =IF(OR(J77="",N77=""),"",IF(J77=N77,"sí","no")) | R77: =IF(OR(K77="",O77=""),"",IF(K77=O77,"sí","no")) | U77: Ninguno de los dos fragmentos usa el sentido "drogado"; ambos parecen literales/figurados distintos. Candidato a reemplazo, re-correr el pipeline para este término.
A78: CUR-077 | B78: guarda | C78: Forma de llamar la atención. Significa "mira" (imperativo del verbo mirar) en italiano. | D78: diccionarioargentino.com | E78: Vos, tu vieja y tu papá / ¡Guarda!... / Cuidensé porque anda suelta | F78: Chorra · Edmundo Rivero (1959) | G78: Yo asi le responderia / Guarda tu confiteria sultan / De Constantinopla... | H78: Rosas orientales · Julián Aguirre | I78: Tomas Borda | J78: polisemico_interno | K78: A | M78: Valentín Garfi | N78: polisemico_interno | O78: A | Q78: =IF(OR(J78="",N78=""),"",IF(J78=N78,"sí","no")) | R78: =IF(OR(K78="",O78=""),"",IF(K78=O78,"sí","no"))
A79: CUR-078 | B79: gota | C79: Volumen pequeño de agua u otro líquido delimitado casi completamente por superficies libres y generalmente con forma cercana a la de una esfera. | D79: Wikcionario | E79: Y cómo volver a ser el mismo / Si no me queda ni una gota de amor / Que no te haya dado esta mañana | F79: Laberinto De Pasiones · Comida China | G79: Nacidas a la luz de las estrellas / Y cubiertas de gotas de rocío / Algo del cielo de la noche en ellas | H79: Mensaje · Felipe Boero | I79: Tomas Borda | J79: espanol_general | K79: B | M79: Valentín Garfi | N79: espanol_general | O79: B | Q79: =IF(OR(J79="",N79=""),"",IF(J79=N79,"sí","no")) | R79: =IF(OR(K79="",O79=""),"",IF(K79=O79,"sí","no"))
A80: CUR-079 | B80: corte | C80: Sinonimo de "tipo" "osea" y "como" | D80: diccionarioargentino.com | E80: 'Tamo re puesto y no para la moto / Todo' lo' podere' corte Kakaroto / Logi, no te peine', no salí' en la foto | F80: KAKAROTO · El Noba | G80: Volvió el turrito, el que siempre hace desastre / Corte 6 a.m. te paso a busca' en el Lander / Tomamos esa rola y la seguimo' re | H80: Del Año · El Noba (2021) | I80: Tomas Borda | J80: polisemico_interno | K80: A | M80: Valentín Garfi | N80: polisemico_interno | O80: A | Q80: =IF(OR(J80="",N80=""),"",IF(J80=N80,"sí","no")) | R80: =IF(OR(K80="",O80=""),"",IF(K80=O80,"sí","no"))
A81: CUR-080 | B81: batir | C81: Delatar | D81: diccionarioargentino.com | E81: Al zonzo, llaman chabón / Y al vivo le baten rana / La guita o el vento es | F81: Milonga Lunfarda · Edmundo Rivero (1972) | G81: I destroy my pain con un bate, mamá / So I am the líder en mi vida, no hay chance | H81: KAMIKAZE · Sofía Gabanna (2023) | I81: Tomas Borda | J81: polisemico_interno | M81: Valentín Garfi | N81: polisemico_interno | Q81: =IF(OR(J81="",N81=""),"",IF(J81=N81,"sí","no")) | R81: =IF(OR(K81="",O81=""),"",IF(K81=O81,"sí","no")) | U81: B usa "bate" (el objeto/palo), no el verbo "batir" en sentido de delatar. Candidato a revisar "El Ciruja" (tango clásico con mucho lunfardo) como fuente alternativa, o re-correr el pipeline.
A82: CUR-081 | B82: muñeca | C82: Habilidad, destreza. | D82: Wikcionario | E82: Por más que no lo crea yo / Ya la muñeca se acabo / Es seguro que un novio tendrás | F82: El tiempo pasa y se va · Carlos Javier Beltrán (1982) | G82: sensación / Si soy fiera sé que, en cambio, tengo un cutis de muñeca / Los que dicen que soy chueca no me han visto en camisón | H82: Se Dice de Mí · Tita Merello (1955) | I82: Tomas Borda | J82: polisemico_interno | K82: A | M82: Valentín Garfi | N82: polisemico_interno | O82: A | Q82: =IF(OR(J82="",N82=""),"",IF(J82=N82,"sí","no")) | R82: =IF(OR(K82="",O82=""),"",IF(K82=O82,"sí","no"))
A83: CUR-082 | B83: ciego | C83: Jugador al que le han tocado malas cartas. | D83: Wikcionario | E83: Condenados, lejos del sol / Nacimos ciegos, nacimos muertos / Salimos del pozo a cavar sus tumbas | F83: Pedagogía de la venganza · Cienfuegos (2021) | G83: Los que al mirar no se hacen / Ciegos por gritar / Sin pretender sen premiados | H83: Rugen Sus Voces · D-mente | I83: Tomas Borda | J83: polisemico_interno | K83: B | M83: Valentín Garfi | N83: polisemico_interno | O83: B | Q83: =IF(OR(J83="",N83=""),"",IF(J83=N83,"sí","no")) | R83: =IF(OR(K83="",O83=""),"",IF(K83=O83,"sí","no"))
A84: CUR-083 | B84: bacán | C84: Persona de alto nivel de vida, muy cómoda y acomodada. | D84: diccionarioargentino.com | E84: Del barrio la mondiola sos el más rana / Y te llaman garufa por lo bacán; / Tenés más pretensiones que bataclana | F84: Garufa · Tita Merello (1968) | G84: Pebeta de mi barrio, papa, papusa / Que andás paseando en auto con un bacán / Que te has cortado el pelo como se usa | H84: Pompas · Roberto Goyeneche (1967) | I84: Tomas Borda | J84: lunfardo_sin_homonimo | K84: B | M84: Valentín Garfi | N84: lunfardo_sin_homonimo | O84: B | Q84: =IF(OR(J84="",N84=""),"",IF(J84=N84,"sí","no")) | R84: =IF(OR(K84="",O84=""),"",IF(K84=O84,"sí","no"))
A85: CUR-084 | B85: quebrar | C85: Escabiar hasta vomitar | D85: diccionarioargentino.com | E85: ¿No ven que soy gotán? / Me quiebro en mi canción / Como un puñal de acero | F85: Yo soy el tango · Miguel Caló | G85: El que a tu guacha se llevó / Y el que en el baile te re quebró | H85: KAKAROTO · El Noba | I85: Tomas Borda | J85: polisemico_interno | M85: Valentín Garfi | N85: polisemico_interno | Q85: =IF(OR(J85="",N85=""),"",IF(J85=N85,"sí","no")) | R85: =IF(OR(K85="",O85=""),"",IF(K85=O85,"sí","no")) | U85: Ninguno de los dos fragmentos refleja "emborracharse hasta vomitar"; B es sobre un paso de baile. Candidato a reemplazo, re-correr el pipeline para este término.
A86: CUR-085 | B86: cristal | C86: Pieza de vidrio u otra sustancia transparente o semitransparente que se coloca en el hueco de una ventana o una vitrina. | D86: Wikcionario | E86: la brisa, rumor de melodía / Y nos darán las fuentes su canto de cristal / El día que me quieras endulzará sus cuerdas el pájaro cantor | F86: El Dia Que Me Quieras · Carlos Gardel (1934) | G86: "¿tus cosa'?, hola, ¿qué tal?" / Es otra noche que vuelvo a llenar la copa 'e cristal / Todo' saben la' consecuencia' de jugar con lo' metal' | H86: Oye Baby · Zaramay (2020) | I86: Tomas Borda | J86: espanol_general | K86: B | M86: Valentín Garfi | N86: espanol_general | O86: B | Q86: =IF(OR(J86="",N86=""),"",IF(J86=N86,"sí","no")) | R86: =IF(OR(K86="",O86=""),"",IF(K86=O86,"sí","no"))
A87: CUR-086 | B87: gato | C87: Hombre que anda con muchas mujeres (no necesariamente prostitutas), también puede ser usado para hablar con un amigo. | D87: diccionarioargentino.com | E87: Donde el pichón se cansó de esperar / Pone en el plato liebre por gato / Cosa que a todos nos puede pasar | F87: El Show Del Perro Salchicha · María Elena Walsh (1966) | G87: Me etiquetó en su burra, 'tamo' chelo / Ese gato hatea, 'tamo' chelo / 'Tam-tam-tamo' chelo | H87: Tamo Chelo · El Noba (2021) | I87: Tomas Borda | J87: polisemico_interno | K87: B | M87: Valentín Garfi | N87: falso_amigo | O87: B | P87: Persona nacida en Madrid (coloq., Esp.) | Q87: =IF(OR(J87="",N87=""),"",IF(J87=N87,"sí","no")) | R87: =IF(OR(K87="",O87=""),"",IF(K87=O87,"sí","no"))
A88: CUR-087 | B88: compadrón | C88: Hombre que trata de imitar al compadrito, pero que carece de la cultura y buenas maneras de él. | D88: Wikcionario | E88: soy fiera, que camino a lo malevo / Que soy chueca y que me muevo con un aire compadrón / Que parezco Leguisamo, mi nariz es puntiaguda | F88: Se Dice de Mí · Tita Merello (1955) | G88: Yo soy propia hermana entera / De chiclana y compadrón / Si me gano el morfi diario | H88: Arrabalera · Tita Merello (1955) | I88: Tomas Borda | J88: lunfardo_sin_homonimo | K88: B | M88: Valentín Garfi | N88: lunfardo_sin_homonimo | O88: B | Q88: =IF(OR(J88="",N88=""),"",IF(J88=N88,"sí","no")) | R88: =IF(OR(K88="",O88=""),"",IF(K88=O88,"sí","no"))
A89: CUR-088 | B89: colgar | C89: Olvidar algo o no prestar atención. | D89: diccionarioargentino.com | E89: Y vo' sabé' que soy yo / El que la colgó en el Falcon / El que a tu guacha se llevó | F89: KAKAROTO · El Noba | G89: Buscando esa gatita que le guste el peligro / Patente tapada, tiro un cuelgue y nos re vimo' / ¿Y ahora qué vamo' a hacer? | H89: Del Año · El Noba (2021) | I89: Tomas Borda | J89: polisemico_interno | K89: B | M89: Valentín Garfi | N89: polisemico_interno | O89: B | Q89: =IF(OR(J89="",N89=""),"",IF(J89=N89,"sí","no")) | R89: =IF(OR(K89="",O89=""),"",IF(K89=O89,"sí","no"))
A90: CUR-089 | B90: verde | C90: Sinónimo de dólares, moneda estadounidense. Un palo verde son mil dólares. | D90: diccionarioargentino.com | E90: Pero acá si somos hombres, y hacemos correr la sangre / Hablame de verdes, de billetes, de mil y quinientos / No me gustan las cazafortuna' y | F90: Freestyle Session #5 · Zaramay (2019) | G90: Como tú, era pálido y lejano / Negro el pelo, los ojos verde gris / Y eran suaves sus manos, y eran sus versos tristes | H90: Tal vez será tu voz · Lidia Borda (2011) | I90: Tomas Borda | J90: polisemico_interno | K90: A | M90: Valentín Garfi | N90: polisemico_interno | O90: A | Q90: =IF(OR(J90="",N90=""),"",IF(J90=N90,"sí","no")) | R90: =IF(OR(K90="",O90=""),"",IF(K90=O90,"sí","no"))
A91: CUR-090 | B91: atado | C91: Paquete de cigarrillos. | D91: Wikcionario | E91: congelo las palabras que nacen y mueren en mi! / Tanto tiempo estuve atado en el frió de tus manos / Tanto tiempo encerrado en el frió | F91: Te Amo · Dar Sangre (2008) | G91: Con un poco 'e estilo acá to' lo logramo' / Los tengo afuera con el perro atado / Esperan a que calle pa' mete' un bocado | H91: Hello Cotto · Duki (2017) | I91: Tomas Borda | J91: polisemico_interno | M91: Valentín Garfi | N91: polisemico_interno | Q91: =IF(OR(J91="",N91=""),"",IF(J91=N91,"sí","no")) | R91: =IF(OR(K91="",O91=""),"",IF(K91=O91,"sí","no")) | U91: Ninguno de los dos fragmentos usa el sentido "paquete de cigarrillos"; ambos son el participio literal de "atar". Candidato a reemplazo, re-correr el pipeline para este término.

Sheet Resumen
A1: Avance
A2: Términos | B2: =COUNTIF('Anotación'!$A$2:$A$91,"?*")
A3: Con anotador 1 | B3: =COUNTIF('Anotación'!$J$2:$J$91,"?*")
A4: Con anotador 2 | B4: =COUNTIF('Anotación'!$N$2:$N$91,"?*")
A5: Con capa final | B5: =COUNTIF('Anotación'!$S$2:$S$91,"?*")
A6: Acuerdo en capa | B6: =IFERROR(COUNTIF('Anotación'!$Q$2:$Q$91,"sí")/(COUNTIF('Anotación'!$Q$2:$Q$91,"sí")+COUNTIF('Anotación'!$Q$2:$Q$91,"no")),"")
A7: Acuerdo en fragmento | B7: =IFERROR(COUNTIF('Anotación'!$R$2:$R$91,"sí")/(COUNTIF('Anotación'!$R$2:$R$91,"sí")+COUNTIF('Anotación'!$R$2:$R$91,"no")),"")
A9: Capa final | B9: Términos
A10: falso_amigo | B10: =COUNTIF('Anotación'!$S$2:$S$91,"falso_amigo")
A11: polisemico_interno | B11: =COUNTIF('Anotación'!$S$2:$S$91,"polisemico_interno")
A12: lunfardo_sin_homonimo | B12: =COUNTIF('Anotación'!$S$2:$S$91,"lunfardo_sin_homonimo")
A13: espanol_general | B13: =COUNTIF('Anotación'!$S$2:$S$91,"espanol_general")
